edspdf/__init__.py
edspdf/lazy_collection.py
edspdf/pipeline.py
edspdf/registry.py
edspdf/structures.py
edspdf/trainable_pipe.py
edspdf/accelerators/__init__.py
edspdf/accelerators/base.py
edspdf/accelerators/multiprocessing.py
edspdf/data/__init__.py
edspdf/data/base.py
edspdf/data/converters.py
edspdf/data/files.py
edspdf/data/pandas.py
edspdf/data/parquet.py
edspdf/layers/__init__.py
edspdf/layers/box_transformer.py
edspdf/layers/relative_attention.py
edspdf/layers/sinusoidal_embedding.py
edspdf/layers/vocabulary.py
edspdf/pipes/__init__.py
edspdf/pipes/aggregators/__init__.py
edspdf/pipes/aggregators/simple.py
edspdf/pipes/classifiers/__init__.py
edspdf/pipes/classifiers/dummy.py
edspdf/pipes/classifiers/mask.py
edspdf/pipes/classifiers/random.py
edspdf/pipes/classifiers/trainable.py
edspdf/pipes/embeddings/__init__.py
edspdf/pipes/embeddings/box_layout_embedding.py
edspdf/pipes/embeddings/box_layout_preprocessor.py
edspdf/pipes/embeddings/box_transformer.py
edspdf/pipes/embeddings/embedding_combiner.py
edspdf/pipes/embeddings/huggingface_embedding.py
edspdf/pipes/embeddings/simple_text_embedding.py
edspdf/pipes/embeddings/sub_box_cnn_pooler.py
edspdf/pipes/extractors/__init__.py
edspdf/pipes/extractors/pdfminer.py
edspdf/processing/__init__.py
edspdf/processing/multiprocessing.py
edspdf/processing/simple.py
edspdf/processing/utils.py
edspdf/utils/__init__.py
edspdf/utils/alignment.py
edspdf/utils/collections.py
edspdf/utils/file_system.py
edspdf/utils/lazy_module.py
edspdf/utils/optimization.py
edspdf/utils/package.py
edspdf/utils/random.py
edspdf/utils/torch.py
edspdf/visualization/__init__.py
edspdf/visualization/annotations.py
edspdf/visualization/merge.py
edspdf-0.9.3.dist-info/METADATA
edspdf-0.9.3.dist-info/WHEEL
edspdf-0.9.3.dist-info/entry_points.txt
edspdf-0.9.3.dist-info/licenses/LICENSE
edspdf-0.9.3.dist-info/RECORD
