Metadata-Version: 2.3
Name: edspdf
Version: 0.9.3
Summary: Smart text extraction from PDF documents
Project-URL: homepage, https://github.com/aphp/edspdf/
Project-URL: repository, https://github.com/aphp/edspdf/
Project-URL: documentation, https://aphp.github.io/edspdf/
Author-email: Perceval Wajsburt <perceval.wajsburt-ext@aphp.fr>, Alice Calliger <alice.calliger-ext@aphp.fr>, Basile Dura <basile.dura-ext@aphp.fr>
License: Copyright 2021 Assistance Publique - Hôpitaux de Paris
Requires-Python: !=3.8.1,<4.0,>3.7.6
Requires-Dist: accelerate<1.0.0,>=0.12.0
Requires-Dist: anyascii>=0.3.2
Requires-Dist: attrs>=23.1
Requires-Dist: build>=0.10.0
Requires-Dist: catalogue>=2.0
Requires-Dist: confit>=0.7.0
Requires-Dist: dill
Requires-Dist: foldedtensor>=0.3.3
Requires-Dist: fsspec; python_version >= '3.8'
Requires-Dist: fsspec<2023.1.0; python_version < '3.8'
Requires-Dist: loguru
Requires-Dist: networkx>=2.6
Requires-Dist: pdfminer-six; python_version >= '3.8'
Requires-Dist: pdfminer-six<20231228,>=20220319; python_version < '3.8'
Requires-Dist: pyarrow
Requires-Dist: pydantic>=1.2
Requires-Dist: pypdfium2>=4.0
Requires-Dist: regex
Requires-Dist: rich-logger>=0.3
Requires-Dist: safetensors>=0.3
Requires-Dist: scikit-learn<2.0.0,>=1.0.2
Requires-Dist: toml
Requires-Dist: torch>1.0.0
Requires-Dist: tqdm>=4.64
